Workbook

Sheet Инструкция
A1: Юнит-экономика новой службы доставки еды
A3: Учебный проект: Подгорный Максим, Колледж Skypro, направление «Бизнес-аналитик».
A5: Что считает модель: сколько бизнес зарабатывает с одного заказа, сколько тратит на привлечение клиента, когда выйдет в плюс и когда окупятся вложения.
A7: Как пользоваться:
A8: 1. Лист «Модель»: жёлтые ячейки с синими цифрами — это вводные данные. Их можно менять, всё остальное пересчитается само.
A9: 2. Лист «Окупаемость»: график накопленной прибыли по трём сценариям (пессимистичный, базовый, оптимистичный).
A10: 3. Лист «Вывод»: короткий текст с результатами. Он обновляется вместе с цифрами.
A12: Важно: все цифры — учебные допущения, а не данные реальной компании. Их можно заменить на реальные, если появится заказчик.
A13: Допущение модели: прибыль в месяц считается одинаковой с первого месяца (без периода раскрутки), налоги не учитываются.

Sheet Модель
A1: Модель юнит-экономики доставки еды
A2: Жёлтые ячейки с синими цифрами — вводные данные (допущения). Остальное считается формулами.
A4: Показатель | B4: Пессимистичный | C4: Базовый | D4: Оптимистичный | E4: Комментарий / допущение
A5: ВВОДНЫЕ ДАННЫЕ
A6: Средний чек, ₽ | B6: 800 | C6: 900 | D6: 950 | E6: Допущение: средний чек доставки готовой еды
A7: Заказов в месяц | B7: 900 | C7: 1500 | D7: 1900 | E7: Допущение: спрос в месяц
A8: Себестоимость блюд, % от чека | B8: 0.4 | C8: 0.35 | D8: 0.34 | E8: Допущение: продукты и приготовление
A9: Доставка курьеру, ₽ за заказ | B9: 170 | C9: 150 | D9: 140 | E9: Допущение: оплата курьера за один заказ
A10: Упаковка, ₽ за заказ | B10: 30 | C10: 25 | D10: 22 | E10: Допущение
A11: Комиссия эквайринга, % от чека | B11: 0.02 | C11: 0.02 | D11: 0.02 | E11: Допущение: комиссия за онлайн-оплату
A12: Реклама в месяц, ₽ | B12: 200000 | C12: 150000 | D12: 180000 | E12: Допущение: расходы на привлечение клиентов
A13: Новых клиентов в месяц | B13: 250 | C13: 300 | D13: 400 | E13: Допущение: сколько клиентов приходит с рекламы
A14: Постоянные расходы в месяц, ₽ | B14: 310000 | C14: 310000 | D14: 310000 | E14: Допущение: аренда кухни, зарплата повара и администратора, прочее
A15: Стартовые вложения, ₽ | B15: 600000 | C15: 600000 | D15: 600000 | E15: Допущение: оборудование, запуск сайта, первый запас продуктов
A17: РАСЧЁТ НА ОДИН ЗАКАЗ
A18: Себестоимость блюд, ₽ | B18: =B6*B8 -> 320 | C18: =C6*C8 -> 315 | D18: =D6*D8 -> 323 | E18: Чек × доля себестоимости
A19: Эквайринг, ₽ | B19: =B6*B11 -> 16 | C19: =C6*C11 -> 18 | D19: =D6*D11 -> 19 | E19: Чек × комиссия
A20: Переменные расходы на заказ, ₽ | B20: =B18+B9+B10+B19 -> 536 | C20: =C18+C9+C10+C19 -> 508 | D20: =D18+D9+D10+D19 -> 504 | E20: Блюда + курьер + упаковка + эквайринг
A21: Прибыль с заказа (до постоянных расходов), ₽ | B21: =B6-B20 -> 264 | C21: =C6-C20 -> 392 | D21: =D6-D20 -> 446 | E21: Чек минус переменные расходы
A22: Маржинальность заказа, % | B22: =IF(B6=0,0,B21/B6) -> 0.33 | C22: =IF(C6=0,0,C21/C6) -> 0.43555556 | D22: =IF(D6=0,0,D21/D6) -> 0.46947368 | E22: Прибыль с заказа / чек
A23: Стоимость привлечения клиента (CAC), ₽ | B23: =IF(B13=0,0,B12/B13) -> 800 | C23: =IF(C13=0,0,C12/C13) -> 500 | D23: =IF(D13=0,0,D12/D13) -> 450 | E23: Реклама / новые клиенты
A25: РАСЧЁТ ЗА МЕСЯЦ И ОКУПАЕМОСТЬ
A26: Выручка в месяц, ₽ | B26: =B6*B7 -> 720000 | C26: =C6*C7 -> 1350000 | D26: =D6*D7 -> 1805000 | E26: Чек × заказы
A27: Прибыль с заказов в месяц, ₽ | B27: =B21*B7 -> 237600 | C27: =C21*C7 -> 588000 | D27: =D21*D7 -> 847400 | E27: Прибыль с заказа × заказы
A28: Прибыль в месяц после рекламы и постоянных расходов, ₽ | B28: =B27-B12-B14 -> -272400 | C28: =C27-C12-C14 -> 128000 | D28: =D27-D12-D14 -> 357400 | E28: Прибыль с заказов минус реклама и постоянные расходы
A29: Точка безубыточности, заказов в месяц | B29: =IF(B21<=0,"невозможна",ROUNDUP((B12+B14)/B21,0)) -> 1932 | C29: =IF(C21<=0,"невозможна",ROUNDUP((C12+C14)/C21,0)) -> 1174 | D29: =IF(D21<=0,"невозможна",ROUNDUP((D12+D14)/D21,0)) -> 1099 | E29: Сколько заказов нужно, чтобы выйти в ноль
A30: Запас прочности, % | B30: =IF(ISNUMBER(B29),IF(B7=0,0,(B7-B29)/B7),"-") -> -1.1466667 | C30: =IF(ISNUMBER(C29),IF(C7=0,0,(C7-C29)/C7),"-") -> 0.21733333 | D30: =IF(ISNUMBER(D29),IF(D7=0,0,(D7-D29)/D7),"-") -> 0.42157895 | E30: Насколько спрос выше точки безубыточности
A31: Окупаемость вложений, месяцев | B31: =IF(B28>0,ROUNDUP(B15/B28,0),"не окупается") -> не окупается | C31: =IF(C28>0,ROUNDUP(C15/C28,0),"не окупается") -> 5 | D31: =IF(D28>0,ROUNDUP(D15/D28,0),"не окупается") -> 2 | E31: Стартовые вложения / прибыль в месяц
A32: Итог | B32: =IF(B28>0,"Прибыльно","Убыточно") -> Убыточно | C32: =IF(C28>0,"Прибыльно","Убыточно") -> Прибыльно | D32: =IF(D28>0,"Прибыльно","Убыточно") -> Прибыльно
A34: Допущение: прибыль в месяц одинакова с первого месяца, налоги не учтены. Все цифры учебные.

Sheet Окупаемость
A1: Накопленная прибыль по месяцам, ₽ (с учётом стартовых вложений)
A3: Месяц | B3: Пессимистичный | C3: Базовый | D3: Оптимистичный
A4: 0 | B4: =-Модель!B$15+$A4*Модель!B$28 -> -600000 | C4: =-Модель!C$15+$A4*Модель!C$28 -> -600000 | D4: =-Модель!D$15+$A4*Модель!D$28 -> -600000
A5: 1 | B5: =-Модель!B$15+$A5*Модель!B$28 -> -872400 | C5: =-Модель!C$15+$A5*Модель!C$28 -> -472000 | D5: =-Модель!D$15+$A5*Модель!D$28 -> -242600
A6: 2 | B6: =-Модель!B$15+$A6*Модель!B$28 -> -1144800 | C6: =-Модель!C$15+$A6*Модель!C$28 -> -344000 | D6: =-Модель!D$15+$A6*Модель!D$28 -> 114800
A7: 3 | B7: =-Модель!B$15+$A7*Модель!B$28 -> -1417200 | C7: =-Модель!C$15+$A7*Модель!C$28 -> -216000 | D7: =-Модель!D$15+$A7*Модель!D$28 -> 472200
A8: 4 | B8: =-Модель!B$15+$A8*Модель!B$28 -> -1689600 | C8: =-Модель!C$15+$A8*Модель!C$28 -> -88000 | D8: =-Модель!D$15+$A8*Модель!D$28 -> 829600
A9: 5 | B9: =-Модель!B$15+$A9*Модель!B$28 -> -1962000 | C9: =-Модель!C$15+$A9*Модель!C$28 -> 40000 | D9: =-Модель!D$15+$A9*Модель!D$28 -> 1187000
A10: 6 | B10: =-Модель!B$15+$A10*Модель!B$28 -> -2234400 | C10: =-Модель!C$15+$A10*Модель!C$28 -> 168000 | D10: =-Модель!D$15+$A10*Модель!D$28 -> 1544400
A11: 7 | B11: =-Модель!B$15+$A11*Модель!B$28 -> -2506800 | C11: =-Модель!C$15+$A11*Модель!C$28 -> 296000 | D11: =-Модель!D$15+$A11*Модель!D$28 -> 1901800
A12: 8 | B12: =-Модель!B$15+$A12*Модель!B$28 -> -2779200 | C12: =-Модель!C$15+$A12*Модель!C$28 -> 424000 | D12: =-Модель!D$15+$A12*Модель!D$28 -> 2259200
A13: 9 | B13: =-Модель!B$15+$A13*Модель!B$28 -> -3051600 | C13: =-Модель!C$15+$A13*Модель!C$28 -> 552000 | D13: =-Модель!D$15+$A13*Модель!D$28 -> 2616600
A14: 10 | B14: =-Модель!B$15+$A14*Модель!B$28 -> -3324000 | C14: =-Модель!C$15+$A14*Модель!C$28 -> 680000 | D14: =-Модель!D$15+$A14*Модель!D$28 -> 2974000
A15: 11 | B15: =-Модель!B$15+$A15*Модель!B$28 -> -3596400 | C15: =-Модель!C$15+$A15*Модель!C$28 -> 808000 | D15: =-Модель!D$15+$A15*Модель!D$28 -> 3331400
... A28: 24 | B28: =-Модель!B$15+$A28*Модель!B$28 -> -7137600 | C28: =-Модель!C$15+$A28*Модель!C$28 -> 2472000 | D28: =-Модель!D$15+$A28*Модель!D$28 -> 7977600

Sheet Вывод
A1: Вывод по проекту
A3: ="Базовый сценарий: с одного заказа остаётся "&TEXT(Модель!C21,"#,##0")&" ₽ при среднем чеке "&TEXT(Модель!C6,"#,##0")&" ₽ (маржинальность "&TEXT(Модель!C22,"0%")&")." -> Базовый сценарий: с одного заказа остаётся 392 ₽ при среднем чеке 900 ₽ (маржинальность 44%).
A4: ="Привлечение одного клиента стоит около "&TEXT(Модель!C23,"#,##0")&" ₽. Прибыль после рекламы и постоянных расходов: "&TEXT(Модель!C28,"#,##0")&" ₽ в месяц." -> Привлечение одного клиента стоит около 500 ₽. Прибыль после рекламы и постоянных расходов: 128,000 ₽ в месяц.
A5: =IF(ISNUMBER(Модель!C29),"Чтобы выйти в ноль, нужно не менее "&TEXT(Модель!C29,"#,##0")&" заказов в месяц, в базовом сценарии их "&TEXT(Модель!C7,"#,##0")&".","При таких вводных проект не выйдет в ноль: прибыль с заказа отрицательная.") -> Чтобы выйти в ноль, нужно не менее 1,174 заказов в месяц, в базовом сценарии их 1,500.
A6: =IF(ISNUMBER(Модель!C31),"Стартовые вложения окупятся примерно за "&Модель!C31&" мес.","В базовом сценарии вложения не окупаются.") -> Стартовые вложения окупятся примерно за 5 мес.
A7: ="Пессимистичный сценарий: "&IF(Модель!B28>0,"проект остаётся прибыльным","проект убыточен")&". Оптимистичный сценарий: окупаемость "&IF(ISNUMBER(Модель!D31),Модель!D31&" мес.","не достигается.") -> Пессимистичный сценарий: проект убыточен. Оптимистичный сценарий: окупаемость 2 мес.
A8: Рекомендация: запускать проект стоит, если реально получить не меньше заказов, чем в точке безубыточности. Самые сильные рычаги — средний чек, себестоимость блюд и стоимость курьера.
